lms/__init__.py
lms/grader.py
lms/lms.py
lms_grader-0.0.6.dist-info/METADATA
lms_grader-0.0.6.dist-info/WHEEL
lms_grader-0.0.6.dist-info/entry_points.txt
lms_grader-0.0.6.dist-info/RECORD
